{
    "compound_radicals": [
      { "radical": "二", "components": ["一", "一"], "meaning": "Two" },
      { "radical": "三", "components": ["一", "一", "一"], "meaning": "Three (Often used as a component)" },
      { "radical": "兦", "components": ["亠", "乚"], "meaning": "Run away / Vanish" },
      { "radical": "內", "components": ["冂", "入"], "meaning": "Inside" },
      { "radical": "冃", "components": ["冂", "二"], "meaning": "Hat / Cap" },
      { "radical": "卝", "components": ["丩", "丩"], "meaning": "Bair / Grass" },
      { "radical": "占", "components": ["卜", "口"], "meaning": "Divination" },
      { "radical": "舌", "components": ["千", "口"], "meaning": "Tongue (Note: 千 is composed of 丿 and 十)" },
      { "radical": "吉", "components": ["士", "口"], "meaning": "Lucky" },
      { "radical": "吏", "components": ["一", "史"], "meaning": "Official" },
      { "radical": "吞", "components": ["天", "口"], "meaning": "Swallow" },
      { "radical": "夯", "components": ["大", "力"], "meaning": "Ram / Heavy work" },
      { "radical": "尖", "components": ["小", "大"], "meaning": "Sharp / Pointed" },
      { "radical": "尘", "components": ["小", "土"], "meaning": "Dust" },
      { "radical": "尤", "components": ["尢", "丶"], "meaning": "Especially" },
      { "radical": "岩", "components": ["山", "石"], "meaning": "Rock / Cliff" },
      { "radical": "島", "components": ["山", "鳥"], "meaning": "Island" },
      { "radical": "忘", "components": ["亡", "心"], "meaning": "Forget" },
      { "radical": "忠", "components": ["中", "心"], "meaning": "Loyal" },
      { "radical": "春", "components": ["三", "人", "日"], "meaning": "Spring" },
      { "radical": "是", "components": ["日", "正"], "meaning": "Is / Correct" },
      { "radical": "杳", "components": ["木", "日"], "meaning": "Dark / Remote" },
      { "radical": "李", "components": ["木", "子"], "meaning": "Plum" },
      { "radical": "歪", "components": ["不", "正"], "meaning": "Crooked" },
      { "radical": "氼", "components": ["人", "水"], "meaning": "Drown" },
      { "radical": "焚", "components": ["木", "木", "火"], "meaning": "Burn" },
      { "radical": "災", "components": ["巛", "火"], "meaning": "Disaster" },
      { "radical": "父", "components": ["八", "乂"], "meaning": "Father" },
      { "radical": "男", "components": ["田", "力"], "meaning": "Male" },
      { "radical": "界", "components": ["田", "介"], "meaning": "Boundary" },
      { "radical": "看", "components": ["手", "目"], "meaning": "Look" },
      { "radical": "相", "components": ["木", "目"], "meaning": "Appearance / Each other" },
      { "radical": "碧", "components": ["王", "白", "石"], "meaning": "Jade green" },
      { "radical": "祭", "components": ["月", "又", "示"], "meaning": "Sacrifice" },
      { "radical": "罕", "components": ["网", "干"], "meaning": "Rare" },
      { "radical": "老", "components": ["土", "丿", "匕"], "meaning": "Old" },
      { "radical": "考", "components": ["老", "丂"], "meaning": "Test" },
      { "radical": "耆", "components": ["老", "日"], "meaning": "Senior" },
      { "radical": "者", "components": ["老", "白"], "meaning": "Person who..." },
      { "radical": "耍", "components": ["而", "女"], "meaning": "Play / Frolic" },
      { "radical": "聞", "components": ["門", "耳"], "meaning": "Hear" },
      { "radical": "胃", "components": ["田", "肉"], "meaning": "Stomach" },
      { "radical": "臭", "components": ["自", "犬"], "meaning": "Stink" },
      { "radical": "至", "components": ["一", "厶", "土"], "meaning": "Arrive" },
      { "radical": "舅", "components": ["臼", "男"], "meaning": "Uncle" },
      { "radical": "航", "components": ["舟", "亢"], "meaning": "Sailing" },
      { "radical": "茁", "components": ["艸", "出"], "meaning": "Sprout" },
      { "radical": "苗", "components": ["艸", "田"], "meaning": "Seedling" },
      { "radical": "衷", "components": ["衣", "中"], "meaning": "Inner feelings" },
      { "radical": "見", "components": ["目", "儿"], "meaning": "See" },
      { "radical": "解", "components": ["角", "刀", "牛"], "meaning": "Explain / Untie" },
      { "radical": "詞", "components": ["言", "司"], "meaning": "Word" },
      { "radical": "谷", "components": ["八", "口"], "meaning": "Valley" },
      { "radical": "豆", "components": ["一", "口", "丷"], "meaning": "Bean" },
      { "radical": "贅", "components": ["敖", "貝"], "meaning": "Superfluous" },
      { "radical": "赫", "components": ["赤", "赤"], "meaning": "Grand / Red" },
      { "radical": "走", "components": ["土", "止"], "meaning": "Walk" },
      { "radical": "趕", "components": ["走", "旱"], "meaning": "Hurry" },
      { "radical": "軍", "components": ["冖", "車"], "meaning": "Army" },
      { "radical": "醉", "components": ["酉", "卒"], "meaning": "Drunk" },
      { "radical": "野", "components": ["里", "予"], "meaning": "Wild" },
      { "radical": "鑑", "components": ["金", "監"], "meaning": "Mirror / Inspect" },
      { "radical": "音", "components": ["立", "日"], "meaning": "Sound" },
      { "radical": "香", "components": ["禾", "日"], "meaning": "Fragrance" },
      { "radical": "鮮", "components": ["魚", "羊"], "meaning": "Fresh" },
      { "radical": "鼻", "components": ["自", "田", "丌"], "meaning": "Nose" }
    ]
  }